{"stat.walkOneCm":54247322,"achievement.openInventory":15110,"stat.horseOneCm":21647614,"stat.leaveGame":206,"stat.damageTaken":10929285,"stat.flyOneCm":46323661,"stat.deaths":92,"stat.drop":5207,"stat.jump":190921,"stat.swimOneCm":2025561,"stat.playOneMinute":10862458,"stat.fallOneCm":4119990,"stat.climbOneCm":14370,"stat.damageDealt":10,"achievement.exploreAllBiomes":{"value":0,"progress":["ForestHills","Beach","Forest","Ocean","Plains","Desert","Taiga","Extreme Hills","Swampland"]},"stat.diveOneCm":1908193}