{"stat.walkOneCm":45665295,"achievement.openInventory":10566,"stat.horseOneCm":29423024,"stat.leaveGame":133,"stat.damageTaken":14084085,"stat.flyOneCm":29421299,"stat.deaths":84,"stat.drop":4125,"stat.jump":156015,"stat.swimOneCm":763810,"stat.playOneMinute":9190635,"stat.fallOneCm":3701396,"stat.climbOneCm":39909,"stat.damageDealt":140,"achievement.exploreAllBiomes":{"value":0,"progress":["ForestHills","Beach","Forest","Ocean","Plains","Desert","Taiga","Extreme Hills","Swampland"]},"stat.diveOneCm":787588}